Metadata-Version: 1.0
Name: Bino-GaussianDist
Version: 0.1
Summary: Gaussian and Binomial distributions
Home-page: UNKNOWN
Author: Namratha Sri Mateti
Author-email: UNKNOWN
License: UNKNOWN
Platform: UNKNOWN
